autocluster/__init__.py
autocluster/algorithms.py
autocluster/autocluster.py
autocluster/build_config_space.py
autocluster/decode_logs.py
autocluster/evaluators.py
autocluster/preprocess_data.py
autocluster/random_sampling_optimizer.py
autocluster/warmstarter.py
autocluster/log_helper/__init__.py
autocluster/log_helper/log_helper.py
autocluster/utils/__init__.py
autocluster/utils/clusterutils.py
autocluster/utils/constants.py
autocluster/utils/logutils.py
autocluster/utils/metafeatures.py
autocluster/utils/plotting.py
autocluster/utils/stringutils.py
autocluster-0.5.3.dist-info/LICENSE
autocluster-0.5.3.dist-info/METADATA
autocluster-0.5.3.dist-info/WHEEL
autocluster-0.5.3.dist-info/top_level.txt
autocluster-0.5.3.dist-info/RECORD
