Metadata-Version: 2.1
Name: autocluster
Version: 0.5.3
Summary: Automated machine learning toolkit for performing clustering tasks.
Home-page: https://github.com/wywongbd/autocluster
Author: Wong Wen Yan
Author-email: wywongbd@gmail.com
License: BSD-3-clause
Download-URL: https://pypi.org/project/autocluster/
Keywords: automl,clustering,bayesian-optimization,hyperparameter-optimization
Platform: UNKNOWN
License-File: LICENSE
Requires-Dist: joblib
Requires-Dist: cycler
Requires-Dist: kiwisolver
Requires-Dist: matplotlib
Requires-Dist: numpy
Requires-Dist: pandas
Requires-Dist: pyparsing
Requires-Dist: python-dateutil
Requires-Dist: pytz
Requires-Dist: scikit-learn
Requires-Dist: scipy
Requires-Dist: six
Requires-Dist: sklearn
